LICENSE
MANIFEST.in
README.md
requirements-dev.txt
requirements.txt
setup.cfg
setup.py
notouch/__init__.py
notouch/app.py
notouch/routes.py
notouch/server.py
notouch/util.py
notouch/version.py
notouch.egg-info/PKG-INFO
notouch.egg-info/SOURCES.txt
notouch.egg-info/dependency_links.txt
notouch.egg-info/entry_points.txt
notouch.egg-info/requires.txt
notouch.egg-info/top_level.txt
notouch/handlers/__init__.py
notouch/handlers/api.py
notouch/handlers/main.py
notouch/handlers/util.py
scripts/dhcpdump_parser.py
tests/api_tests/__init__.py
tests/api_tests/__init__.pyc
tests/api_tests/fixtures.py
tests/api_tests/fixtures.pyc
tests/api_tests/test_dhcp.py
tests/api_tests/util.py
tests/api_tests/util.pyc
tests/api_tests/__pycache__/test_dhcp.cpython-27-PYTEST.pyc