Metadata-Version: 1.1
Name: notouch
Version: 0.3
Summary: Notouch Physical Machine Installer Automation Service
Home-page: https://github.com/dropbox/notouch
Author: Matthew B Cote
Author-email: mcot@dropbox.com
License: Apache
Download-URL: https://github.com/dropbox/notouch/archive/master.tar.gz
Platform: UNKNOWN
Classifier: Programming Language :: Python
Classifier: Topic :: Software Development
Classifier: Topic :: Software Development :: Libraries
Classifier: Topic :: Software Development :: Libraries :: Python Modules
